Design/perceptron.v
`define CIRCLE_SUM_VAL 4
`define CROSS_SUM_VAL 11

module perceptron #(parameter WIDTH = 25, WEIGHTS = 4) (
    input [WIDTH-1:0] in,
    input en,
    input clk,
    output reg [1:0] out,
    output reg ready
);
    localparam reg_weights_size      = $clog2(WIDTH);
    localparam reg_weights_vals_size = $clog2(WEIGHTS);
    localparam buffor_size           = reg_weights_size - reg_weights_vals_size;
    integer i;

    localparam fsm_mac_multiply   = 0;
    localparam fsm_mac_accumulate = 1;

    reg [reg_weights_size-1:0] r_accumulate;
    reg [reg_weights_size-1:0] r_state_index;
    reg [1:0]          r_state_mac;
    reg [1:0]          r_multiply;
    reg [1:0]          r_weights [0:WIDTH-1];

    initial begin
        for (i=0; i<WIDTH; i = i+1) begin
            case (i)
            12:           r_weights[i] = 2'b11;
            0,4,20,24:    r_weights[i] = 2'b10; //CROSS WEIGHTS
            2,10,14,22:   r_weights[i] = 2'b01; //CIRCLE WEIGHTS
            default:      r_weights[i] = 2'b00; //NEUTRAL
            endcase 
        end 
        i = 0;
        r_state_index = 0;
        r_state_mac = 0;
    end

    always @(posedge clk && en) begin
    
        if(r_state_index <= WIDTH) begin
            case (r_state_mac)
                fsm_mac_multiply: begin
                    //multiplying is combinational, empty cycle;
                    r_accumulate <= (r_state_index == 0) ? 0 : r_accumulate; 
                    r_state_mac <= r_state_mac +1;
                end
                fsm_mac_accumulate: begin
                    r_accumulate <= r_accumulate + {{buffor_size{1'b0}},r_multiply};
                    r_state_mac <= 0;
                    r_state_index <= r_state_index + 1;
                end
                default:  r_state_mac <= 0;
            endcase

        end else begin
            r_state_index <= 0;
        end
    end 

    always @(*) begin
        r_multiply = (r_state_index < WIDTH) ? r_weights[r_state_index] & {reg_weights_vals_size{in[r_state_index]}} : 0;
        ready = (r_state_index == WIDTH + 1) ? 1:0;
        if      ((r_accumulate == `CROSS_SUM_VAL)  && (ready))    out = 2'b10;
        else if ((r_accumulate == `CIRCLE_SUM_VAL) && (ready))    out = 2'b01;
        else                                                      out = 2'b00;
    end
endmodule

TB/perceptron_tb.sv
//iverilog -o Simulation/perceptron_tb perceptron_tb.v && vvp Simulation/perceptron_tb && gtkwave "Simulation/perceptron_tb.gtkw" --rcvar 'fontname_signals Monospace 15' --rcvar 'fontname_waves Monospace 12'
`timescale  1ns/1ps
`include "Design/perceptron.v"
`define TB_PATH "Simulation/perceptron_tb.vcd"
`define MAX_SIM_TIME #30000

`define CROSS_VAL  {1'b1, 24'h15_11_51}
`define CIRCLE_VAL {1'b0, 24'h45_45_44}

`define CASE_FSM(st_val,jmp_val,code,state_name)\ 
st_val: begin \
    code\
state_name <= jmp_val; end 

`define NEXT_STATE  if(ready_dut && r_state_change_delay > 5) begin\
                        state_tb <= state_tb + 1;\
                        r_state_change_delay <= 0;\
                    end


module perceptron_tb();

reg [3:0] state_tb; 
reg clk_tb;
reg [6:0] r_state_change_delay;


reg [24:0] input_val_dut;
reg en_dut;
reg clk_dut;
wire ready_dut;
wire [1:0] out_dut;
perceptron perceptron_inst(
    .in(input_val_dut),
    .en(en_dut),
    .clk(clk_dut),
    .out(out_dut),
    .ready(ready_dut)
);


initial begin
    clk_tb = 0;
    state_tb = 0;
    en_dut = 0;
    clk_dut = 0;
    r_state_change_delay = 0;
end
initial begin  
    forever begin
        #10 clk_tb = ~clk_tb;
    end
end
always @(posedge clk_tb) begin
    clk_dut <= ~clk_dut;
    r_state_change_delay <= r_state_change_delay+1;
end



initial `MAX_SIM_TIME state_tb = 4'hF;


always @(posedge clk_tb) begin
    case (state_tb)
    0: begin
        {en_dut, input_val_dut} <= {1'd0,25'd0};

        state_tb <= state_tb + 1;
    end
    1: begin
        {en_dut, input_val_dut} <= {1'd1,`CIRCLE_VAL};
        
        `NEXT_STATE
    end
    2: begin
        {en_dut, input_val_dut} <= {1'd1,`CROSS_VAL};

        `NEXT_STATE
    end
    3: begin
        {en_dut, input_val_dut} <= {1'd1,`CIRCLE_VAL};

        `NEXT_STATE
    end
    4: begin
        {en_dut, input_val_dut} <= {1'd1,`CROSS_VAL};

        `NEXT_STATE
    end
    5: begin
        {en_dut, input_val_dut} <= {1'd1,`CROSS_VAL};
        
        `NEXT_STATE
    end
    default: begin
        #30
       $finish();
    end
    endcase    

end







initial begin // file save
    $dumpfile(`TB_PATH);
    $dumpvars;
    $dumpon;
end
endmodule

Simulation/perceptron_tb.vcd
$date
	Sat May 10 16:00:47 2025
$end
$version
	Icarus Verilog
$end
$timescale
	1ps
$end
$scope module perceptron_tb $end
$var wire 1 ! ready_dut $end
$var wire 2 " out_dut [1:0] $end
$var reg 1 # clk_dut $end
$var reg 1 $ clk_tb $end
$var reg 1 % en_dut $end
$var reg 25 & input_val_dut [24:0] $end
$var reg 7 ' r_state_change_delay [6:0] $end
$var reg 4 ( state_tb [3:0] $end
$scope module perceptron_inst $end
$var wire 1 # clk $end
$var wire 1 % en $end
$var wire 25 ) in [24:0] $end
$var parameter 32 * WEIGHTS $end
$var parameter 32 + WIDTH $end
$var parameter 33 , buffor_size $end
$var parameter 32 - fsm_mac_accumulate $end
$var parameter 32 . fsm_mac_multiply $end
$var parameter 32 / reg_weights_size $end
$var parameter 32 0 reg_weights_vals_size $end
$var reg 2 1 out [1:0] $end
$var reg 5 2 r_accumulate [4:0] $end
$var reg 2 3 r_multiply [1:0] $end
$var reg 5 4 r_state_index [4:0] $end
$var reg 2 5 r_state_mac [1:0] $end
$var reg 1 ! ready $end
$var integer 32 6 i [31:0] $end
$upscope $end
$upscope $end
$enddefinitions $end
$comment Show the parameter values. $end
$dumpall
b10 0
b101 /
b0 .
b1 -
b11 ,
b11001 +
b100 *
$end
#0
$dumpvars
b0 6
b0 5
b0 4
bx0 3
bx 2
b0 1
bx )
b0 (
b0 '
bx &
0%
0$
0#
b0 "
0!
$end
#10000
b0 3
b1 '
1#
b1 (
b0 &
b0 )
1$
#20000
0$
#30000
1%
b10001010100010101000100 &
b10001010100010101000100 )
b10 '
0#
1$
#40000
0$
#50000
b1 5
b0 2
b11 '
1#
1$
#60000
0$
#70000
b100 '
0#
1$
#80000
0$
#90000
b1 4
b0 5
b101 '
1#
1$
#100000
0$
#110000
b110 '
0#
1$
#120000
0$
#130000
b1 5
b111 '
1#
1$
#140000
0$
#150000
b1000 '
0#
1$
#160000
0$
#170000
b1 3
b10 4
b0 5
b1001 '
1#
1$
#180000
0$
#190000
b1010 '
0#
1$
#200000
0$
#210000
b1 5
b1011 '
1#
1$
#220000
0$
#230000
b1100 '
0#
1$
#240000
0$
#250000
b0 3
b11 4
b0 5
b1 2
b1101 '
1#
1$
#260000
0$
#270000
b1110 '
0#
1$
#280000
0$
#290000
b1 5
b1111 '
1#
1$
#300000
0$
#310000
b10000 '
0#
1$
#320000
0$
#330000
b100 4
b0 5
b10001 '
1#
1$
#340000
0$
#350000
b10010 '
0#
1$
#360000
0$
#370000
b1 5
b10011 '
1#
1$
#380000
0$
#390000
b10100 '
0#
1$
#400000
0$
#410000
b101 4
b0 5
b10101 '
1#
1$
#420000
0$
#430000
b10110 '
0#
1$
#440000
0$
#450000
b1 5
b10111 '
1#
1$
#460000
0$
#470000
b11000 '
0#
1$
#480000
0$
#490000
b110 4
b0 5
b11001 '
1#
1$
#500000
0$
#510000
b11010 '
0#
1$
#520000
0$
#530000
b1 5
b11011 '
1#
1$
#540000
0$
#550000
b11100 '
0#
1$
#560000
0$
#570000
b111 4
b0 5
b11101 '
1#
1$
#580000
0$
#590000
b11110 '
0#
1$
#600000
0$
#610000
b1 5
b11111 '
1#
1$
#620000
0$
#630000
b100000 '
0#
1$
#640000
0$
#650000
b1000 4
b0 5
b100001 '
1#
1$
#660000
0$
#670000
b100010 '
0#
1$
#680000
0$
#690000
b1 5
b100011 '
1#
1$
#700000
0$
#710000
b100100 '
0#
1$
#720000
0$
#730000
b1001 4
b0 5
b100101 '
1#
1$
#740000
0$
#750000
b100110 '
0#
1$
#760000
0$
#770000
b1 5
b100111 '
1#
1$
#780000
0$
#790000
b101000 '
0#
1$
#800000
0$
#810000
b1 3
b1010 4
b0 5
b101001 '
1#
1$
#820000
0$
#830000
b101010 '
0#
1$
#840000
0$
#850000
b1 5
b101011 '
1#
1$
#860000
0$
#870000
b101100 '
0#
1$
#880000
0$
#890000
b0 3
b1011 4
b0 5
b10 2
b101101 '
1#
1$
#900000
0$
#910000
b101110 '
0#
1$
#920000
0$
#930000
b1 5
b101111 '
1#
1$
#940000
0$
#950000
b110000 '
0#
1$
#960000
0$
#970000
b1100 4
b0 5
b110001 '
1#
1$
#980000
0$
#990000
b110010 '
0#
1$
#1000000
0$
#1010000
b1 5
b110011 '
1#
1$
#1020000
0$
#1030000
b110100 '
0#
1$
#1040000
0$
#1050000
b1101 4
b0 5
b110101 '
1#
1$
#1060000
0$
#1070000
b110110 '
0#
1$
#1080000
0$
#1090000
b1 5
b110111 '
1#
1$
#1100000
0$
#1110000
b111000 '
0#
1$
#1120000
0$
#1130000
b1 3
b1110 4
b0 5
b111001 '
1#
1$
#1140000
0$
#1150000
b111010 '
0#
1$
#1160000
0$
#1170000
b1 5
b111011 '
1#
1$
#1180000
0$
#1190000
b111100 '
0#
1$
#1200000
0$
#1210000
b0 3
b1111 4
b0 5
b11 2
b111101 '
1#
1$
#1220000
0$
#1230000
b111110 '
0#
1$
#1240000
0$
#1250000
b1 5
b111111 '
1#
1$
#1260000
0$
#1270000
b1000000 '
0#
1$
#1280000
0$
#1290000
b10000 4
b0 5
b1000001 '
1#
1$
#1300000
0$
#1310000
b1000010 '
0#
1$
#1320000
0$
#1330000
b1 5
b1000011 '
1#
1$
#1340000
0$
#1350000
b1000100 '
0#
1$
#1360000
0$
#1370000
b10001 4
b0 5
b1000101 '
1#
1$
#1380000
0$
#1390000
b1000110 '
0#
1$
#1400000
0$
#1410000
b1 5
b1000111 '
1#
1$
#1420000
0$
#1430000
b1001000 '
0#
1$
#1440000
0$
#1450000
b10010 4
b0 5
b1001001 '
1#
1$
#1460000
0$
#1470000
b1001010 '
0#
1$
#1480000
0$
#1490000
b1 5
b1001011 '
1#
1$
#1500000
0$
#1510000
b1001100 '
0#
1$
#1520000
0$
#1530000
b10011 4
b0 5
b1001101 '
1#
1$
#1540000
0$
#1550000
b1001110 '
0#
1$
#1560000
0$
#1570000
b1 5
b1001111 '
1#
1$
#1580000
0$
#1590000
b1010000 '
0#
1$
#1600000
0$
#1610000
b10100 4
b0 5
b1010001 '
1#
1$
#1620000
0$
#1630000
b1010010 '
0#
1$
#1640000
0$
#1650000
b1 5
b1010011 '
1#
1$
#1660000
0$
#1670000
b1010100 '
0#
1$
#1680000
0$
#1690000
b10101 4
b0 5
b1010101 '
1#
1$
#1700000
0$
#1710000
b1010110 '
0#
1$
#1720000
0$
#1730000
b1 5
b1010111 '
1#
1$
#1740000
0$
#1750000
b1011000 '
0#
1$
#1760000
0$
#1770000
b1 3
b10110 4
b0 5
b1011001 '
1#
1$
#1780000
0$
#1790000
b1011010 '
0#
1$
#1800000
0$
#1810000
b1 5
b1011011 '
1#
1$
#1820000
0$
#1830000
b1011100 '
0#
1$
#1840000
0$
#1850000
b0 3
b10111 4
b0 5
b100 2
b1011101 '
1#
1$
#1860000
0$
#1870000
b1011110 '
0#
1$
#1880000
0$
#1890000
b1 5
b1011111 '
1#
1$
#1900000
0$
#1910000
b1100000 '
0#
1$
#1920000
0$
#1930000
b11000 4
b0 5
b1100001 '
1#
1$
#1940000
0$
#1950000
b1100010 '
0#
1$
#1960000
0$
#1970000
b1 5
b1100011 '
1#
1$
#1980000
0$
#1990000
b1100100 '
0#
1$
#2000000
0$
#2010000
b11001 4
b0 5
b1100101 '
1#
1$
#2020000
0$
#2030000
b1100110 '
0#
1$
#2040000
0$
#2050000
b1 5
b1100111 '
1#
1$
#2060000
0$
#2070000
b1101000 '
0#
1$
#2080000
0$
#2090000
b1 "
b1 1
1!
b11010 4
b0 5
b1101001 '
1#
1$
#2100000
0$
#2110000
b10 (
b0 '
0#
1$
#2120000
0$
#2130000
b0 "
b0 1
0!
b10 3
b0 4
b1 '
1#
b1000101010001000101010001 &
b1000101010001000101010001 )
1$
#2140000
0$
#2150000
b10 '
0#
1$
#2160000
0$
#2170000
b1 5
b0 2
b11 '
1#
1$
#2180000
0$
#2190000
b100 '
0#
1$
#2200000
0$
#2210000
b0 3
b1 4
b0 5
b10 2
b101 '
1#
1$
#2220000
0$
#2230000
b110 '
0#
1$
#2240000
0$
#2250000
b1 5
b111 '
1#
1$
#2260000
0$
#2270000
b1000 '
0#
1$
#2280000
0$
#2290000
b10 4
b0 5
b1001 '
1#
1$
#2300000
0$
#2310000
b1010 '
0#
1$
#2320000
0$
#2330000
b1 5
b1011 '
1#
1$
#2340000
0$
#2350000
b1100 '
0#
1$
#2360000
0$
#2370000
b11 4
b0 5
b1101 '
1#
1$
#2380000
0$
#2390000
b1110 '
0#
1$
#2400000
0$
#2410000
b1 5
b1111 '
1#
1$
#2420000
0$
#2430000
b10000 '
0#
1$
#2440000
0$
#2450000
b10 3
b100 4
b0 5
b10001 '
1#
1$
#2460000
0$
#2470000
b10010 '
0#
1$
#2480000
0$
#2490000
b1 5
b10011 '
1#
1$
#2500000
0$
#2510000
b10100 '
0#
1$
#2520000
0$
#2530000
b0 3
b101 4
b0 5
b100 2
b10101 '
1#
1$
#2540000
0$
#2550000
b10110 '
0#
1$
#2560000
0$
#2570000
b1 5
b10111 '
1#
1$
#2580000
0$
#2590000
b11000 '
0#
1$
#2600000
0$
#2610000
b110 4
b0 5
b11001 '
1#
1$
#2620000
0$
#2630000
b11010 '
0#
1$
#2640000
0$
#2650000
b1 5
b11011 '
1#
1$
#2660000
0$
#2670000
b11100 '
0#
1$
#2680000
0$
#2690000
b111 4
b0 5
b11101 '
1#
1$
#2700000
0$
#2710000
b11110 '
0#
1$
#2720000
0$
#2730000
b1 5
b11111 '
1#
1$
#2740000
0$
#2750000
b100000 '
0#
1$
#2760000
0$
#2770000
b1000 4
b0 5
b100001 '
1#
1$
#2780000
0$
#2790000
b100010 '
0#
1$
#2800000
0$
#2810000
b1 5
b100011 '
1#
1$
#2820000
0$
#2830000
b100100 '
0#
1$
#2840000
0$
#2850000
b1001 4
b0 5
b100101 '
1#
1$
#2860000
0$
#2870000
b100110 '
0#
1$
#2880000
0$
#2890000
b1 5
b100111 '
1#
1$
#2900000
0$
#2910000
b101000 '
0#
1$
#2920000
0$
#2930000
b1010 4
b0 5
b101001 '
1#
1$
#2940000
0$
#2950000
b101010 '
0#
1$
#2960000
0$
#2970000
b1 5
b101011 '
1#
1$
#2980000
0$
#2990000
b101100 '
0#
1$
#3000000
0$
#3010000
b1011 4
b0 5
b101101 '
1#
1$
#3020000
0$
#3030000
b101110 '
0#
1$
#3040000
0$
#3050000
b1 5
b101111 '
1#
1$
#3060000
0$
#3070000
b110000 '
0#
1$
#3080000
0$
#3090000
b11 3
b1100 4
b0 5
b110001 '
1#
1$
#3100000
0$
#3110000
b110010 '
0#
1$
#3120000
0$
#3130000
b1 5
b110011 '
1#
1$
#3140000
0$
#3150000
b110100 '
0#
1$
#3160000
0$
#3170000
b0 3
b1101 4
b0 5
b111 2
b110101 '
1#
1$
#3180000
0$
#3190000
b110110 '
0#
1$
#3200000
0$
#3210000
b1 5
b110111 '
1#
1$
#3220000
0$
#3230000
b111000 '
0#
1$
#3240000
0$
#3250000
b1110 4
b0 5
b111001 '
1#
1$
#3260000
0$
#3270000
b111010 '
0#
1$
#3280000
0$
#3290000
b1 5
b111011 '
1#
1$
#3300000
0$
#3310000
b111100 '
0#
1$
#3320000
0$
#3330000
b1111 4
b0 5
b111101 '
1#
1$
#3340000
0$
#3350000
b111110 '
0#
1$
#3360000
0$
#3370000
b1 5
b111111 '
1#
1$
#3380000
0$
#3390000
b1000000 '
0#
1$
#3400000
0$
#3410000
b10000 4
b0 5
b1000001 '
1#
1$
#3420000
0$
#3430000
b1000010 '
0#
1$
#3440000
0$
#3450000
b1 5
b1000011 '
1#
1$
#3460000
0$
#3470000
b1000100 '
0#
1$
#3480000
0$
#3490000
b10001 4
b0 5
b1000101 '
1#
1$
#3500000
0$
#3510000
b1000110 '
0#
1$
#3520000
0$
#3530000
b1 5
b1000111 '
1#
1$
#3540000
0$
#3550000
b1001000 '
0#
1$
#3560000
0$
#3570000
b10010 4
b0 5
b1001001 '
1#
1$
#3580000
0$
#3590000
b1001010 '
0#
1$
#3600000
0$
#3610000
b1 5
b1001011 '
1#
1$
#3620000
0$
#3630000
b1001100 '
0#
1$
#3640000
0$
#3650000
b10011 4
b0 5
b1001101 '
1#
1$
#3660000
0$
#3670000
b1001110 '
0#
1$
#3680000
0$
#3690000
b1 5
b1001111 '
1#
1$
#3700000
0$
#3710000
b1010000 '
0#
1$
#3720000
0$
#3730000
b10 3
b10100 4
b0 5
b1010001 '
1#
1$
#3740000
0$
#3750000
b1010010 '
0#
1$
#3760000
0$
#3770000
b1 5
b1010011 '
1#
1$
#3780000
0$
#3790000
b1010100 '
0#
1$
#3800000
0$
#3810000
b0 3
b10101 4
b0 5
b1001 2
b1010101 '
1#
1$
#3820000
0$
#3830000
b1010110 '
0#
1$
#3840000
0$
#3850000
b1 5
b1010111 '
1#
1$
#3860000
0$
#3870000
b1011000 '
0#
1$
#3880000
0$
#3890000
b10110 4
b0 5
b1011001 '
1#
1$
#3900000
0$
#3910000
b1011010 '
0#
1$
#3920000
0$
#3930000
b1 5
b1011011 '
1#
1$
#3940000
0$
#3950000
b1011100 '
0#
1$
#3960000
0$
#3970000
b10111 4
b0 5
b1011101 '
1#
1$
#3980000
0$
#3990000
b1011110 '
0#
1$
#4000000
0$
#4010000
b1 5
b1011111 '
1#
1$
#4020000
0$
#4030000
b1100000 '
0#
1$
#4040000
0$
#4050000
b10 3
b11000 4
b0 5
b1100001 '
1#
1$
#4060000
0$
#4070000
b1100010 '
0#
1$
#4080000
0$
#4090000
b1 5
b1100011 '
1#
1$
#4100000
0$
#4110000
b1100100 '
0#
1$
#4120000
0$
#4130000
b0 3
b11001 4
b0 5
b1011 2
b1100101 '
1#
1$
#4140000
0$
#4150000
b1100110 '
0#
1$
#4160000
0$
#4170000
b1 5
b1100111 '
1#
1$
#4180000
0$
#4190000
b1101000 '
0#
1$
#4200000
0$
#4210000
b10 "
b10 1
1!
b11010 4
b0 5
b1101001 '
1#
1$
#4220000
0$
#4230000
b11 (
b0 '
0#
1$
#4240000
0$
#4250000
b0 "
b0 1
0!
b0 4
b1 '
1#
b10001010100010101000100 &
b10001010100010101000100 )
1$
#4260000
0$
#4270000
b10 '
0#
1$
#4280000
0$
#4290000
b1 5
b0 2
b11 '
1#
1$
#4300000
0$
#4310000
b100 '
0#
1$
#4320000
0$
#4330000
b1 4
b0 5
b101 '
1#
1$
#4340000
0$
#4350000
b110 '
0#
1$
#4360000
0$
#4370000
b1 5
b111 '
1#
1$
#4380000
0$
#4390000
b1000 '
0#
1$
#4400000
0$
#4410000
b1 3
b10 4
b0 5
b1001 '
1#
1$
#4420000
0$
#4430000
b1010 '
0#
1$
#4440000
0$
#4450000
b1 5
b1011 '
1#
1$
#4460000
0$
#4470000
b1100 '
0#
1$
#4480000
0$
#4490000
b0 3
b11 4
b0 5
b1 2
b1101 '
1#
1$
#4500000
0$
#4510000
b1110 '
0#
1$
#4520000
0$
#4530000
b1 5
b1111 '
1#
1$
#4540000
0$
#4550000
b10000 '
0#
1$
#4560000
0$
#4570000
b100 4
b0 5
b10001 '
1#
1$
#4580000
0$
#4590000
b10010 '
0#
1$
#4600000
0$
#4610000
b1 5
b10011 '
1#
1$
#4620000
0$
#4630000
b10100 '
0#
1$
#4640000
0$
#4650000
b101 4
b0 5
b10101 '
1#
1$
#4660000
0$
#4670000
b10110 '
0#
1$
#4680000
0$
#4690000
b1 5
b10111 '
1#
1$
#4700000
0$
#4710000
b11000 '
0#
1$
#4720000
0$
#4730000
b110 4
b0 5
b11001 '
1#
1$
#4740000
0$
#4750000
b11010 '
0#
1$
#4760000
0$
#4770000
b1 5
b11011 '
1#
1$
#4780000
0$
#4790000
b11100 '
0#
1$
#4800000
0$
#4810000
b111 4
b0 5
b11101 '
1#
1$
#4820000
0$
#4830000
b11110 '
0#
1$
#4840000
0$
#4850000
b1 5
b11111 '
1#
1$
#4860000
0$
#4870000
b100000 '
0#
1$
#4880000
0$
#4890000
b1000 4
b0 5
b100001 '
1#
1$
#4900000
0$
#4910000
b100010 '
0#
1$
#4920000
0$
#4930000
b1 5
b100011 '
1#
1$
#4940000
0$
#4950000
b100100 '
0#
1$
#4960000
0$
#4970000
b1001 4
b0 5
b100101 '
1#
1$
#4980000
0$
#4990000
b100110 '
0#
1$
#5000000
0$
#5010000
b1 5
b100111 '
1#
1$
#5020000
0$
#5030000
b101000 '
0#
1$
#5040000
0$
#5050000
b1 3
b1010 4
b0 5
b101001 '
1#
1$
#5060000
0$
#5070000
b101010 '
0#
1$
#5080000
0$
#5090000
b1 5
b101011 '
1#
1$
#5100000
0$
#5110000
b101100 '
0#
1$
#5120000
0$
#5130000
b0 3
b1011 4
b0 5
b10 2
b101101 '
1#
1$
#5140000
0$
#5150000
b101110 '
0#
1$
#5160000
0$
#5170000
b1 5
b101111 '
1#
1$
#5180000
0$
#5190000
b110000 '
0#
1$
#5200000
0$
#5210000
b1100 4
b0 5
b110001 '
1#
1$
#5220000
0$
#5230000
b110010 '
0#
1$
#5240000
0$
#5250000
b1 5
b110011 '
1#
1$
#5260000
0$
#5270000
b110100 '
0#
1$
#5280000
0$
#5290000
b1101 4
b0 5
b110101 '
1#
1$
#5300000
0$
#5310000
b110110 '
0#
1$
#5320000
0$
#5330000
b1 5
b110111 '
1#
1$
#5340000
0$
#5350000
b111000 '
0#
1$
#5360000
0$
#5370000
b1 3
b1110 4
b0 5
b111001 '
1#
1$
#5380000
0$
#5390000
b111010 '
0#
1$
#5400000
0$
#5410000
b1 5
b111011 '
1#
1$
#5420000
0$
#5430000
b111100 '
0#
1$
#5440000
0$
#5450000
b0 3
b1111 4
b0 5
b11 2
b111101 '
1#
1$
#5460000
0$
#5470000
b111110 '
0#
1$
#5480000
0$
#5490000
b1 5
b111111 '
1#
1$
#5500000
0$
#5510000
b1000000 '
0#
1$
#5520000
0$
#5530000
b10000 4
b0 5
b1000001 '
1#
1$
#5540000
0$
#5550000
b1000010 '
0#
1$
#5560000
0$
#5570000
b1 5
b1000011 '
1#
1$
#5580000
0$
#5590000
b1000100 '
0#
1$
#5600000
0$
#5610000
b10001 4
b0 5
b1000101 '
1#
1$
#5620000
0$
#5630000
b1000110 '
0#
1$
#5640000
0$
#5650000
b1 5
b1000111 '
1#
1$
#5660000
0$
#5670000
b1001000 '
0#
1$
#5680000
0$
#5690000
b10010 4
b0 5
b1001001 '
1#
1$
#5700000
0$
#5710000
b1001010 '
0#
1$
#5720000
0$
#5730000
b1 5
b1001011 '
1#
1$
#5740000
0$
#5750000
b1001100 '
0#
1$
#5760000
0$
#5770000
b10011 4
b0 5
b1001101 '
1#
1$
#5780000
0$
#5790000
b1001110 '
0#
1$
#5800000
0$
#5810000
b1 5
b1001111 '
1#
1$
#5820000
0$
#5830000
b1010000 '
0#
1$
#5840000
0$
#5850000
b10100 4
b0 5
b1010001 '
1#
1$
#5860000
0$
#5870000
b1010010 '
0#
1$
#5880000
0$
#5890000
b1 5
b1010011 '
1#
1$
#5900000
0$
#5910000
b1010100 '
0#
1$
#5920000
0$
#5930000
b10101 4
b0 5
b1010101 '
1#
1$
#5940000
0$
#5950000
b1010110 '
0#
1$
#5960000
0$
#5970000
b1 5
b1010111 '
1#
1$
#5980000
0$
#5990000
b1011000 '
0#
1$
#6000000
0$
#6010000
b1 3
b10110 4
b0 5
b1011001 '
1#
1$
#6020000
0$
#6030000
b1011010 '
0#
1$
#6040000
0$
#6050000
b1 5
b1011011 '
1#
1$
#6060000
0$
#6070000
b1011100 '
0#
1$
#6080000
0$
#6090000
b0 3
b10111 4
b0 5
b100 2
b1011101 '
1#
1$
#6100000
0$
#6110000
b1011110 '
0#
1$
#6120000
0$
#6130000
b1 5
b1011111 '
1#
1$
#6140000
0$
#6150000
b1100000 '
0#
1$
#6160000
0$
#6170000
b11000 4
b0 5
b1100001 '
1#
1$
#6180000
0$
#6190000
b1100010 '
0#
1$
#6200000
0$
#6210000
b1 5
b1100011 '
1#
1$
#6220000
0$
#6230000
b1100100 '
0#
1$
#6240000
0$
#6250000
b11001 4
b0 5
b1100101 '
1#
1$
#6260000
0$
#6270000
b1100110 '
0#
1$
#6280000
0$
#6290000
b1 5
b1100111 '
1#
1$
#6300000
0$
#6310000
b1101000 '
0#
1$
#6320000
0$
#6330000
b1 "
b1 1
1!
b11010 4
b0 5
b1101001 '
1#
1$
#6340000
0$
#6350000
b100 (
b0 '
0#
1$
#6360000
0$
#6370000
b0 "
b0 1
0!
b10 3
b0 4
b1 '
1#
b1000101010001000101010001 &
b1000101010001000101010001 )
1$
#6380000
0$
#6390000
b10 '
0#
1$
#6400000
0$
#6410000
b1 5
b0 2
b11 '
1#
1$
#6420000
0$
#6430000
b100 '
0#
1$
#6440000
0$
#6450000
b0 3
b1 4
b0 5
b10 2
b101 '
1#
1$
#6460000
0$
#6470000
b110 '
0#
1$
#6480000
0$
#6490000
b1 5
b111 '
1#
1$
#6500000
0$
#6510000
b1000 '
0#
1$
#6520000
0$
#6530000
b10 4
b0 5
b1001 '
1#
1$
#6540000
0$
#6550000
b1010 '
0#
1$
#6560000
0$
#6570000
b1 5
b1011 '
1#
1$
#6580000
0$
#6590000
b1100 '
0#
1$
#6600000
0$
#6610000
b11 4
b0 5
b1101 '
1#
1$
#6620000
0$
#6630000
b1110 '
0#
1$
#6640000
0$
#6650000
b1 5
b1111 '
1#
1$
#6660000
0$
#6670000
b10000 '
0#
1$
#6680000
0$
#6690000
b10 3
b100 4
b0 5
b10001 '
1#
1$
#6700000
0$
#6710000
b10010 '
0#
1$
#6720000
0$
#6730000
b1 5
b10011 '
1#
1$
#6740000
0$
#6750000
b10100 '
0#
1$
#6760000
0$
#6770000
b0 3
b101 4
b0 5
b100 2
b10101 '
1#
1$
#6780000
0$
#6790000
b10110 '
0#
1$
#6800000
0$
#6810000
b1 5
b10111 '
1#
1$
#6820000
0$
#6830000
b11000 '
0#
1$
#6840000
0$
#6850000
b110 4
b0 5
b11001 '
1#
1$
#6860000
0$
#6870000
b11010 '
0#
1$
#6880000
0$
#6890000
b1 5
b11011 '
1#
1$
#6900000
0$
#6910000
b11100 '
0#
1$
#6920000
0$
#6930000
b111 4
b0 5
b11101 '
1#
1$
#6940000
0$
#6950000
b11110 '
0#
1$
#6960000
0$
#6970000
b1 5
b11111 '
1#
1$
#6980000
0$
#6990000
b100000 '
0#
1$
#7000000
0$
#7010000
b1000 4
b0 5
b100001 '
1#
1$
#7020000
0$
#7030000
b100010 '
0#
1$
#7040000
0$
#7050000
b1 5
b100011 '
1#
1$
#7060000
0$
#7070000
b100100 '
0#
1$
#7080000
0$
#7090000
b1001 4
b0 5
b100101 '
1#
1$
#7100000
0$
#7110000
b100110 '
0#
1$
#7120000
0$
#7130000
b1 5
b100111 '
1#
1$
#7140000
0$
#7150000
b101000 '
0#
1$
#7160000
0$
#7170000
b1010 4
b0 5
b101001 '
1#
1$
#7180000
0$
#7190000
b101010 '
0#
1$
#7200000
0$
#7210000
b1 5
b101011 '
1#
1$
#7220000
0$
#7230000
b101100 '
0#
1$
#7240000
0$
#7250000
b1011 4
b0 5
b101101 '
1#
1$
#7260000
0$
#7270000
b101110 '
0#
1$
#7280000
0$
#7290000
b1 5
b101111 '
1#
1$
#7300000
0$
#7310000
b110000 '
0#
1$
#7320000
0$
#7330000
b11 3
b1100 4
b0 5
b110001 '
1#
1$
#7340000
0$
#7350000
b110010 '
0#
1$
#7360000
0$
#7370000
b1 5
b110011 '
1#
1$
#7380000
0$
#7390000
b110100 '
0#
1$
#7400000
0$
#7410000
b0 3
b1101 4
b0 5
b111 2
b110101 '
1#
1$
#7420000
0$
#7430000
b110110 '
0#
1$
#7440000
0$
#7450000
b1 5
b110111 '
1#
1$
#7460000
0$
#7470000
b111000 '
0#
1$
#7480000
0$
#7490000
b1110 4
b0 5
b111001 '
1#
1$
#7500000
0$
#7510000
b111010 '
0#
1$
#7520000
0$
#7530000
b1 5
b111011 '
1#
1$
#7540000
0$
#7550000
b111100 '
0#
1$
#7560000
0$
#7570000
b1111 4
b0 5
b111101 '
1#
1$
#7580000
0$
#7590000
b111110 '
0#
1$
#7600000
0$
#7610000
b1 5
b111111 '
1#
1$
#7620000
0$
#7630000
b1000000 '
0#
1$
#7640000
0$
#7650000
b10000 4
b0 5
b1000001 '
1#
1$
#7660000
0$
#7670000
b1000010 '
0#
1$
#7680000
0$
#7690000
b1 5
b1000011 '
1#
1$
#7700000
0$
#7710000
b1000100 '
0#
1$
#7720000
0$
#7730000
b10001 4
b0 5
b1000101 '
1#
1$
#7740000
0$
#7750000
b1000110 '
0#
1$
#7760000
0$
#7770000
b1 5
b1000111 '
1#
1$
#7780000
0$
#7790000
b1001000 '
0#
1$
#7800000
0$
#7810000
b10010 4
b0 5
b1001001 '
1#
1$
#7820000
0$
#7830000
b1001010 '
0#
1$
#7840000
0$
#7850000
b1 5
b1001011 '
1#
1$
#7860000
0$
#7870000
b1001100 '
0#
1$
#7880000
0$
#7890000
b10011 4
b0 5
b1001101 '
1#
1$
#7900000
0$
#7910000
b1001110 '
0#
1$
#7920000
0$
#7930000
b1 5
b1001111 '
1#
1$
#7940000
0$
#7950000
b1010000 '
0#
1$
#7960000
0$
#7970000
b10 3
b10100 4
b0 5
b1010001 '
1#
1$
#7980000
0$
#7990000
b1010010 '
0#
1$
#8000000
0$
